skprofiling/__init__.py
skprofiling/classification_report.py
skprofiling/utils.py
skprofiling-0.1.2.dist-info/LICENSE
skprofiling-0.1.2.dist-info/METADATA
skprofiling-0.1.2.dist-info/WHEEL
skprofiling-0.1.2.dist-info/top_level.txt
skprofiling-0.1.2.dist-info/RECORD
